miiiii/__init__.py
miiiii/algos.py
miiiii/block.py
miiiii/datum.py
miiiii/model.py
miiiii/numbs.py
miiiii/param.py
miiiii/plots.py
miiiii/scope.py
miiiii/train.py
miiiii/utils.py
miiiii-0.1.0.dist-info/METADATA
miiiii-0.1.0.dist-info/WHEEL
miiiii-0.1.0.dist-info/RECORD
