Metadata-Version: 2.1
Name: miiiii
Version: 0.1.0
Summary: mechanistic interpretability of irriducible integer identifiers
Author: Noah Syrkis
Author-email: noah@syrkis.com
Requires-Python: >=3.11,<4.0
Classifier: Programming Language :: Python :: 3
Classifier: Programming Language :: Python :: 3.11
Classifier: Programming Language :: Python :: 3.12
Requires-Dist: darkdetect (>=0.8.0,<0.9.0)
Requires-Dist: einops (>=0.8.0,<0.9.0)
Requires-Dist: jax (>=0.4.29,<0.5.0)
Requires-Dist: jupyterlab (>=4.2.2,<5.0.0)
Requires-Dist: matplotlib (>=3.9.0,<4.0.0)
Requires-Dist: numpy-hilbert-curve (>=1.0.1,<2.0.0)
Requires-Dist: oeis (>=2023.3.10,<2024.0.0)
Requires-Dist: optax (>=0.2.2,<0.3.0)
Requires-Dist: pyyaml (>=6.0.1,<7.0.0)
Requires-Dist: requests (>=2.32.2,<3.0.0)
Requires-Dist: scikit-learn (>=1.5.0,<2.0.0)
Requires-Dist: seaborn (>=0.13.2,<0.14.0)
Requires-Dist: streamlit (>=1.35.0,<2.0.0)
Requires-Dist: tqdm (>=4.66.4,<5.0.0)
Requires-Dist: wandb (>=0.17.0,<0.18.0)
